testmcpmathserver/__init__.py
testmcpmathserver/__main__.py
testmcpmathserver/mcp_tools.py
testmcpmathserver-0.1.2.dist-info/METADATA
testmcpmathserver-0.1.2.dist-info/WHEEL
testmcpmathserver-0.1.2.dist-info/entry_points.txt
testmcpmathserver-0.1.2.dist-info/RECORD
