Metadata-Version: 2.4
Name: testmcpmathserver
Version: 0.1.2
Summary: Add your description here
Author-email: Akashns007 <akash.ns@thoughtclan.com>
Requires-Python: >=3.12
Requires-Dist: mcp[cli]>=1.12.3
Requires-Dist: numpy>=2.3.2
Requires-Dist: sympy>=1.14.0
